rpideck/__about__.py
rpideck/__init__.py
rpideck/__main__.py
rpideck/cli/AVR.py
rpideck/cli/DDC.py
rpideck/cli/RPiDeck.py
rpideck/cli/RPiDeckConfig.py
rpideck/cli/SERIAL.py
rpideck/cli/__init__.py
rpideck-0.3.0.dist-info/METADATA
rpideck-0.3.0.dist-info/WHEEL
rpideck-0.3.0.dist-info/entry_points.txt
rpideck-0.3.0.dist-info/licenses/LICENSE
rpideck-0.3.0.dist-info/RECORD
