Metadata-Version: 2.4
Name: rpideck
Version: 0.3.0
Project-URL: Documentation, https://github.com/danielskowronski/RPiDeck
Project-URL: Issues, https://github.com/danielskowronski/RPiDeck/issues
Project-URL: Source, https://github.com/danielskowronski/RPiDeck
Author-email: Daniel Skowroński <daniel@skowron.ski>
License-Expression: MIT
License-File: LICENSE
Classifier: Development Status :: 4 - Beta
Classifier: Programming Language :: Python
Classifier: Programming Language :: Python :: 3.8
Classifier: Programming Language :: Python :: 3.9
Classifier: Programming Language :: Python :: 3.10
Classifier: Programming Language :: Python :: 3.11
Classifier: Programming Language :: Python :: 3.12
Classifier: Programming Language :: Python :: Implementation :: CPython
Classifier: Programming Language :: Python :: Implementation :: PyPy
Requires-Python: >=3.8
Requires-Dist: apscheduler~=3.11.0
Requires-Dist: click~=8.2.1
Requires-Dist: coloredlogs~=15.0.1
Requires-Dist: onkyo-eiscp~=1.2.7
Requires-Dist: pillow~=11.3.0
Requires-Dist: pyserial~=3.5
Requires-Dist: pyyaml~=6.0.2
Requires-Dist: schema~=0.7.7
Requires-Dist: streamdeck~=0.9.7
